icenumerics/__init__.py
icenumerics/colloidalice.py
icenumerics/parameters.py
icenumerics/spins.py
icenumerics/vertices.py
icenumerics/geometry/__init__.py
icenumerics/geometry/honeycomb.py
icenumerics/geometry/square.py
icenumerics-0.1.9.dist-info/METADATA
icenumerics-0.1.9.dist-info/RECORD
icenumerics-0.1.9.dist-info/WHEEL
icenumerics-0.1.9.dist-info/top_level.txt
