Metadata-Version: 2.1
Name: icenumerics
Version: 0.1.9
Summary: Simulations of Colloidal Ice
Home-page: https://github.com/aortiza/icenumerics
Author: Antonio Ortiz-Ambriz
Author-email: aortiza@gmail.com
License: UNKNOWN
Platform: UNKNOWN
Classifier: Programming Language :: Python :: 3
Classifier: License :: OSI Approved :: MIT License
Classifier: Development Status :: 3 - Alpha
Classifier: Operating System :: Microsoft :: Windows
Classifier: Operating System :: MacOS :: MacOS X
Classifier: Operating System :: Unix
Requires-Dist: numpy
Requires-Dist: scipy
Requires-Dist: pandas
Requires-Dist: matplotlib
Requires-Dist: pint
Requires-Dist: jsonpickle
Requires-Dist: magcolloid (>=0.3.8)
